u3m/__init__.py
u3m/generate/__init__.py
u3m/generate/mapAll.py
u3m/generate/merge.py
u3m/generate/workerProcess.py
u3m/map/__init__.py
u3m/map/bldg.py
u3m/map/dsm.py
u3m/map/dtm.py
u3m/map/landcover.py
u3m/map/ndhm.py
u3m/map/tree.py
u3m/map/water.py
u3m/utils/__init__.py
u3m/utils/download_naips.py
u3m/utils/download_tiles.py
u3m/utils/generate_las_boundary.py
u3m/utils/utils.py
u3m-0.1.2.dist-info/licenses/LICENSE
u3m-0.1.2.dist-info/METADATA
u3m-0.1.2.dist-info/WHEEL
u3m-0.1.2.dist-info/top_level.txt
u3m-0.1.2.dist-info/RECORD
