Metadata-Version: 2.4
Name: u3m
Version: 0.1.2
Requires-Python: >=3.10
License-File: LICENSE
Requires-Dist: tqdm
Requires-Dist: numpy
Requires-Dist: opencv-python
Requires-Dist: scikit-image
Requires-Dist: scipy
Requires-Dist: laspy
Requires-Dist: pyproj
Requires-Dist: lazrs[laszip]
Requires-Dist: leafmap
Requires-Dist: xarray
Requires-Dist: rasterio
Requires-Dist: localtileserver
Requires-Dist: ipykernel
Requires-Dist: openrs-python
Requires-Dist: d2spy
Dynamic: license-file
Dynamic: requires-dist
Dynamic: requires-python
